onx/__init__.py
onx/api.py
onx/server/__init__.py
onx/server/app.py
onx/server/errors.py
onx/server/event_loop.py
onx/server/game.py
onx/server/handler.py
onx/settings.py
onx/tui/__init__.py
onx/tui/app.py
onx/tui/events.py
onx/tui/footer.py
onx/tui/grid.py
onx/tui/header.py
onx/tui/tile.py
run.py
onx-0.3.1.dist-info/entry_points.txt
onx-0.3.1.dist-info/LICENSE
onx-0.3.1.dist-info/WHEEL
onx-0.3.1.dist-info/METADATA
onx-0.3.1.dist-info/RECORD
