Metadata-Version: 2.1
Name: onx
Version: 0.3.1
Summary: Noughts & Crosses (Tic Tac Toe) terminal based, client-server online game with your partner through websockets.
Home-page: https://github.com/vyalovvldmr/onx
License: GPL-3.0-or-later
Keywords: Noughts & Crosses,Tic Tac Toe,terminal based game,online game,websockets
Author: Vladimir Vyalov
Author-email: vyalov.v@gmail.com
Requires-Python: >=3.10,<4.0
Classifier: Development Status :: 4 - Beta
Classifier: Environment :: Console
Classifier: Framework :: AsyncIO
Classifier: Intended Audience :: Developers
Classifier: License :: OSI Approved :: GNU General Public License v3 or later (GPLv3+)
Classifier: Operating System :: MacOS
Classifier: Operating System :: Microsoft :: Windows :: Windows 11
Classifier: Operating System :: POSIX :: Linux
Classifier: Programming Language :: Python :: 3
Classifier: Programming Language :: Python :: 3.10
Classifier: Topic :: Games/Entertainment :: Board Games
Classifier: Typing :: Typed
Requires-Dist: aiohttp[speedups] (==3.8.1)
Requires-Dist: cachetools (==5.2.0)
Requires-Dist: click (==8.1.3)
Requires-Dist: pydantic (==1.9.2)
Requires-Dist: pyfiglet (==0.8.post1)
Requires-Dist: single-source (==0.3.0)
Requires-Dist: textual (==0.1.18)
Project-URL: Repository, https://github.com/vyalovvldmr/onx
